taitel_and_dukler_map.py
flowregimemap-0.1.dist-info/METADATA
flowregimemap-0.1.dist-info/WHEEL
flowregimemap-0.1.dist-info/top_level.txt
flowregimemap-0.1.dist-info/RECORD
