Metadata-Version: 2.1
Name: flowregimemap
Version: 0.1
Summary: A Python package to predict flow regimes and plot flow regime maps
Home-page: https://github.com/abdopetroleum/flowregimemap
Author: Abdulrahman Shahin
Author-email: your.email@example.com
Classifier: Programming Language :: Python :: 3
Classifier: License :: OSI Approved :: MIT License
Classifier: Operating System :: OS Independent
Requires-Python: >=3.6
Requires-Dist: numpy
Requires-Dist: matplotlib
